sple_artifacts_uploader/__init__.py
sple_artifacts_uploader/_run.py
sple_artifacts_uploader/artifact_uploader.py
sple_artifacts_uploader/main.py
sple_artifacts_uploader/py.typed
sple_artifacts_uploader-0.1.1.dist-info/LICENSE
sple_artifacts_uploader-0.1.1.dist-info/METADATA
sple_artifacts_uploader-0.1.1.dist-info/WHEEL
sple_artifacts_uploader-0.1.1.dist-info/RECORD
