Metadata-Version: 2.3
Name: sple-artifacts-uploader
Version: 0.1.1
Summary: Configurable and automatable uploader for artifacts.
License: MIT
Author: Avengineers
Author-email: karsten.guenther@kamg.de
Requires-Python: >=3.10,<3.14
Classifier: Development Status :: 2 - Pre-Alpha
Classifier: Intended Audience :: Developers
Classifier: License :: OSI Approved :: MIT License
Classifier: Natural Language :: English
Classifier: Operating System :: OS Independent
Classifier: Programming Language :: Python :: 3
Classifier: Programming Language :: Python :: 3.10
Classifier: Programming Language :: Python :: 3.11
Classifier: Programming Language :: Python :: 3.12
Classifier: Programming Language :: Python :: 3.13
Classifier: Topic :: Software Development :: Libraries
Requires-Dist: py-app-dev (>=2.1.0,<3.0.0)
Requires-Dist: requests (>=2.32.3,<3.0.0)
Requires-Dist: typer (>=0.12.3,<0.13.0)
Project-URL: Bug Tracker, https://github.com/Avengineers/sple-artifacts-uploader/issues
Project-URL: Changelog, https://github.com/Avengineers/sple-artifacts-uploader/blob/develop/CHANGELOG.md
Project-URL: Documentation, https://sple-artifacts-uploader.readthedocs.io
Project-URL: Repository, https://github.com/Avengineers/sple-artifacts-uploader
